{
  "currentScoreValue": 8,
  "currentStartingSpot": [
    53.49416129999999,
    10.1996241
  ],
  "currentClosestGrocery": [
    53.491996699999994,
    10.2068986
  ],
  "currentClosestHealth": [
    53.4935969,
    10.2015082
  ],
  "currentClosestTransit": [
    53.4924422,
    10.195640299999999
  ],
  "currentClosestPreference": [
    53.4943956,
    10.197531999999999
  ],
  "currentTravelMode": "walking",
  "currentGroceryDuration": 12,
  "currentHealthDuration": 10,
  "currentTransitDuration": 6,
  "currentPreferenceDuration": 3,
  "currentStartAddress": "Ulmenliet 20, 21033 Hamburg, Germany",
  "currentClosestGroceryAddress": "Alte Holstenstraße 30/Marktkauf, 21031 Hamburg, Germany",
  "currentClosestHealthAddress": "Ulmenliet 20, 21033 Hamburg, Germany",
  "currentClosestTransitAddress": "Ruselerweg, 21033 Hamburg, Germany",
  "currentClosestPreferenceAddress": "Lohbrügger Kirchstraße 52, 21033 Hamburg, Germany",
  "currentClosestGroceryName": "Edeka Center",
  "currentClosestHealthName": "Prof. Dr. Joachim Westenhöfer",
  "currentClosestTransitName": "Ruselerweg",
  "currentClosestPreferenceName": "Speicherbibliothek Hamburg"
}